MANIFEST.in
README.md
VERSION
setup.cfg
setup.py
erasure/__init__.py
erasure/contracts.py
erasure/crypto.py
erasure/erasure_client.py
erasure/feed.py
erasure/ipfs.py
erasure/post.py
erasure/session.py
erasure/settings.py
erasure/utils.py
erasure.egg-info/PKG-INFO
erasure.egg-info/SOURCES.txt
erasure.egg-info/dependency_links.txt
erasure.egg-info/requires.txt
erasure.egg-info/top_level.txt